{
  "id": "b2c3d4e5-f6a7-8901-bcde-f12345678901",
  "name": "HillSpace Local",
  "values": [
    {
      "key": "baseUrl",
      "value": "http://localhost:3000/api",
      "type": "default",
      "enabled": true
    },
    {
      "key": "accessToken",
      "value": "",
      "type": "secret",
      "enabled": true
    },
    {
      "key": "refreshToken",
      "value": "",
      "type": "secret",
      "enabled": true
    },
    {
      "key": "listingId",
      "value": "",
      "type": "default",
      "enabled": true
    },
    {
      "key": "escrowId",
      "value": "",
      "type": "default",
      "enabled": true
    },
    {
      "key": "verificationId",
      "value": "",
      "type": "default",
      "enabled": true
    }
  ],
  "_postman_variable_scope": "environment"
}
